timed_prompt/__init__.py
timed_prompt/prompt.py
timed_prompt-0.0.3.dist-info/licenses/LICENSE
timed_prompt-0.0.3.dist-info/METADATA
timed_prompt-0.0.3.dist-info/WHEEL
timed_prompt-0.0.3.dist-info/entry_points.txt
timed_prompt-0.0.3.dist-info/top_level.txt
timed_prompt-0.0.3.dist-info/RECORD
