Metadata-Version: 2.4
Name: timed-prompt
Version: 0.0.3
Summary: Cross-platform input/getpass prompt with real timeout (Windows/Linux/macOS)
Author: Muthukumar Subramanian
License-Expression: MIT
Keywords: input,getpass,timeout,prompt,cross-platform,python-tools
Classifier: Programming Language :: Python :: 3
Classifier: Programming Language :: Python :: 3 :: Only
Classifier: Operating System :: OS Independent
Classifier: Environment :: Console
Classifier: Topic :: Software Development :: Quality Assurance
Classifier: Topic :: Software Development :: Libraries :: Python Modules
Classifier: Topic :: Utilities
Requires-Python: >=3.9
License-File: LICENSE
Dynamic: license-file
